examples/document_parser_example.py
examples/embedders_example.py
examples/reranker_example.py
examples/retriever_example.py
mixedbread_ai_haystack/__init__.py
mixedbread_ai_haystack/py.typed
mixedbread_ai_haystack/converters/__init__.py
mixedbread_ai_haystack/converters/document_parser.py
mixedbread_ai_haystack/embedders/__init__.py
mixedbread_ai_haystack/embedders/document_embedder.py
mixedbread_ai_haystack/embedders/text_embedder.py
mixedbread_ai_haystack/rerankers/__init__.py
mixedbread_ai_haystack/rerankers/reranker.py
mixedbread_ai_haystack/retrievers/__init__.py
mixedbread_ai_haystack/retrievers/vector_store_retriever.py
mixedbread_ai_haystack-2.1.3.dist-info/licenses/LICENSE
tests/__init__.py
tests/test_document_embedder.py
tests/test_document_parser.py
tests/test_reranker.py
tests/test_text_embedder.py
tests/test_vector_store_retriever.py
mixedbread_ai_haystack-2.1.3.dist-info/METADATA
mixedbread_ai_haystack-2.1.3.dist-info/WHEEL
mixedbread_ai_haystack-2.1.3.dist-info/top_level.txt
mixedbread_ai_haystack-2.1.3.dist-info/RECORD
