Metadata-Version: 2.4
Name: mixedbread-ai-haystack
Version: 2.1.3
Summary: The official Mixedbread AI integration for Haystack
Author-email: Mixedbread AI <support@mixedbread.com>
License: Apache-2.0
Project-URL: Homepage, https://github.com/mixedbread-ai/mixedbread-ai-haystack
Project-URL: Documentation, https://www.mixedbread.com/api-reference/integrations/haystack
Project-URL: Issues, https://github.com/mixedbread-ai/mixedbread-ai-haystack/issues
Project-URL: Source, https://github.com/mixedbread-ai/mixedbread-ai-haystack
Keywords: haystack,mixedbread,embedding,reranking,parsing,nlp,llm,mixedbread-ai
Classifier: Intended Audience :: Developers
Classifier: License :: OSI Approved :: Apache Software License
Classifier: Operating System :: OS Independent
Classifier: Programming Language :: Python
Classifier: Programming Language :: Python :: 3.9
Classifier: Programming Language :: Python :: 3.10
Classifier: Programming Language :: Python :: 3.11
Classifier: Programming Language :: Python :: 3.12
Classifier: Topic :: Scientific/Engineering :: Artificial Intelligence
Classifier: Topic :: Software Development :: Libraries :: Python Modules
Classifier: Typing :: Typed
Requires-Python: >=3.9
License-File: LICENSE
Requires-Dist: haystack-ai>=2.0.0
Requires-Dist: mixedbread>=0.13.1
Requires-Dist: pydantic>=2.0.0
Provides-Extra: dev
Requires-Dist: pytest>=7.0; extra == "dev"
Requires-Dist: pytest-asyncio>=0.21.0; extra == "dev"
Dynamic: license-file
